Workbook

Sheet README
A1: Tutoring Business Financial Model
A3: As at: | B3: 2026-08-20
A4: Business wound up: | B4: 2026-09-18 (end of school term)
A5: Student identities: | B5: Pseudonymised. Every student appears as "Student NN"; no real name, parent name, email address, or address appears anywhere in this workbook. The mapping from pseudonym to real identity is kept in a file that is not part of this repository.
A7: What this model does
A8: A driver-based financial model of a private tutoring business, built from actual lesson-schedule and billing data for one school term. It derives revenue, cost-to-serve, capacity utilisation, and a provisioned P&L from that data, then explores scenarios and rate/utilisation sensitivity.
A10: Sheet order
A11: • Assumptions
A12: • Data
A13: • Revenue by student
A14: • Cost to serve
A15: • Capacity
A16: • P&L and provisioning
A17: • Scenarios
A18: • Sensitivity
A20: What isn't in this model
A21: No suburb or address field exists anywhere in the source data, so travel cost/time is modelled as a flat weekly figure allocated across students by lesson share, not as a per-suburb distance calculation.

Sheet Assumptions
A1: Assumptions
A2: Every input the model uses lives here, in its own labelled cell. Formulas elsewhere reference these cells; nothing downstream hardcodes a number.
A4: Label | B4: Value | C4: Units | D4: Source / basis
A6: Rates & Lesson Structure
A7: Rate per lesson | B7: 40 | C7: $/lesson | D7: From data: flat $40 per 30-minute lesson across all 37 students (Portfolio Lesson Schedule extract, Term 1 2026).
A8: Standard lesson duration | B8: 30 | C8: min | D8: Confirmed by business owner, 2026-08-20. Not present in source data.
A9: Implied hourly rate | B9: =$B$7/($B$8/60) -> 80 | C9: $/hr | D9: Derived: rate per lesson ÷ (duration ÷ 60).
A11: Statutory & Provisioning
A12: Superannuation provision rate | B12: 0.125 | C12: % | D12: Statutory (ATO) rate, FY2025-26.
A13: Income tax provisioning rate | B13: 0.2 | C13: % | D13: ESTIMATE for provisioning purposes only. Tutoring is being wound up mid financial year; the real liability depends on total income across the whole year, which isn't modelled here. Not a derived or lodged figure.
A15: Working Pattern
A16: Terms per year | B16: 4 | C16: terms | D16: Owner estimate.
A17: Weeks per term | B17: 9 | C17: weeks | D17: Owner estimate. Matches the 9 weekly blocks in the extracted schedule.
A18: Working weeks per year | B18: =$B$16*$B$17 -> 36 | C18: weeks | D18: Derived: terms per year × weeks per term.
A19: Working days per week | B19: 5 | C19: days | D19: From data: 5 populated weekdays per week in the extract.
A20: Max lessons per week (scheduling ceiling) | B20: 37 | C20: lessons | D20: Owner confirmed, 2026-08-20. Equals current scheduled lesson volume. The business is already scheduled at its capacity ceiling; the gap to lessons actually delivered is show-up rate, not spare capacity.
A21: Max teachable hours per week | B21: =$B$20*$B$8/60 -> 18.5 | C21: hrs | D21: Derived: max lessons per week × duration ÷ 60. This is a ceiling on lesson-delivery time; travel time is separate, additive time spent outside it (see Capacity sheet), not subtracted from it.
A23: Travel & Vehicle
A24: Travel time per day | B24: 1.5 | C24: hrs | D24: Owner estimate, flat figure. No per-suburb location data exists in the source, so travel can't be modelled by distance.
A25: Travel time per week | B25: =$B$24*$B$19 -> 7.5 | C25: hrs | D25: Derived: travel time per day × working days per week.
A26: Vehicle insurance | B26: 150 | C26: $/mo | D26: Owner estimate.
A27: Fuel price | B27: 1.8 | C27: $/L | D27: Owner estimate ("generally").
A28: Fuel tank size | B28: 40 | C28: L | D28: Owner estimate.
A29: Tank refill frequency | B29: 1.5 | C29: weeks | D29: Owner estimate.
A30: Insurance cost per working week | B30: =$B$26*12/$B$18 -> 50 | C30: $/wk | D30: Derived: monthly insurance × 12 ÷ working weeks per year.
A31: Fuel cost per week | B31: =$B$28*$B$27/$B$29 -> 48 | C31: $/wk | D31: Derived: tank size × fuel price ÷ refill frequency.
A32: Vehicle running cost per week | B32: =$B$30+$B$31 -> 98 | C32: $/wk | D32: Derived: insurance/week + fuel/week. Modelled flat (not $/km) because no distance data exists to drive a per-km figure.
A34: Scenario Parameters
A35: Scenario switch | B35: 1 | C35: 1/2/3 | D35: 1 = Base (actual), 2 = More students at current rate, 3 = Higher rate, fewer students. Drives the "Selected scenario" callout on the Scenarios sheet.
A36: Scenario 2: lesson volume multiplier | B36: 1.3 | C36: × | D36: Illustrative, adjust as needed. 30% more lesson volume at the current rate.
A37: Scenario 3: rate multiplier | B37: 1.25 | C37: × | D37: Illustrative, adjust as needed. A 25% rate rise.
A38: Scenario 3: lesson volume multiplier | B38: 0.85 | C38: × | D38: Illustrative, adjust as needed. 15% fewer lessons at the higher rate.

Sheet Data
A1: Data
A2: Anonymised lesson schedule, one row per scheduled lesson slot. Extracted from the Portfolio Lesson Schedule sheet (Term 1 2026, 9 weeks); not hand-edited. Source: scripts/extract.py.
A4: Student | B4: Lesson Date | C4: Attended | D4: Duration (min) | E4: Rate ($)
A5: Student 01 | B5: 2026-02-02 | C5: Y | D5: 30 | E5: 40
A6: Student 02 | B6: 2026-02-02 | C6: Y | D6: 30 | E6: 40
A7: Student 03 | B7: 2026-02-02 | C7: Y | D7: 30 | E7: 40
A8: Student 06 | B8: 2026-02-02 | C8: Y | D8: 30 | E8: 40
A9: Student 07 | B9: 2026-02-02 | C9: Y | D9: 30 | E9: 40
A10: Student 08 | B10: 2026-02-02 | C10: Y | D10: 30 | E10: 40
A11: Student 09 | B11: 2026-02-02 | C11: Y | D11: 30 | E11: 40
A12: Student 04 | B12: 2026-02-03 | C12: Y | D12: 30 | E12: 40
A13: Student 05 | B13: 2026-02-03 | C13: Y | D13: 30 | E13: 40
A14: Student 10 | B14: 2026-02-03 | C14: Y | D14: 30 | E14: 40
A15: Student 11 | B15: 2026-02-03 | C15: Y | D15: 30 | E15: 40
A16: Student 12 | B16: 2026-02-03 | C16: N | D16: 30 | E16: 40
... A337: Student 37 | B337: 2026-04-03 | C337: Y | D337: 30 | E337: 40

Sheet Revenue by student
A1: Revenue by student
A3: Student | B3: Lessons scheduled | C3: Lessons delivered | D3: Hours delivered | E3: Gross revenue ($) | F3: Effective hourly rate ($/hr)
A4: Student 01 | B4: =COUNTIFS(Data!$A$5:$A$337,A4) -> 9 | C4: =COUNTIFS(Data!$A$5:$A$337,A4,Data!$C$5:$C$337,"Y") -> 9 | D4: =SUMIFS(Data!$D$5:$D$337,Data!$A$5:$A$337,A4,Data!$C$5:$C$337,"Y")/60 -> 4.5 | E4: =SUMIFS(Data!$E$5:$E$337,Data!$A$5:$A$337,A4,Data!$C$5:$C$337,"Y") -> 360 | F4: =IFERROR(E4/D4,0) -> 80
A5: Student 02 | B5: =COUNTIFS(Data!$A$5:$A$337,A5) -> 9 | C5: =COUNTIFS(Data!$A$5:$A$337,A5,Data!$C$5:$C$337,"Y") -> 9 | D5: =SUMIFS(Data!$D$5:$D$337,Data!$A$5:$A$337,A5,Data!$C$5:$C$337,"Y")/60 -> 4.5 | E5: =SUMIFS(Data!$E$5:$E$337,Data!$A$5:$A$337,A5,Data!$C$5:$C$337,"Y") -> 360 | F5: =IFERROR(E5/D5,0) -> 80
A6: Student 03 | B6: =COUNTIFS(Data!$A$5:$A$337,A6) -> 9 | C6: =COUNTIFS(Data!$A$5:$A$337,A6,Data!$C$5:$C$337,"Y") -> 9 | D6: =SUMIFS(Data!$D$5:$D$337,Data!$A$5:$A$337,A6,Data!$C$5:$C$337,"Y")/60 -> 4.5 | E6: =SUMIFS(Data!$E$5:$E$337,Data!$A$5:$A$337,A6,Data!$C$5:$C$337,"Y") -> 360 | F6: =IFERROR(E6/D6,0) -> 80
A7: Student 04 | B7: =COUNTIFS(Data!$A$5:$A$337,A7) -> 9 | C7: =COUNTIFS(Data!$A$5:$A$337,A7,Data!$C$5:$C$337,"Y") -> 8 | D7: =SUMIFS(Data!$D$5:$D$337,Data!$A$5:$A$337,A7,Data!$C$5:$C$337,"Y")/60 -> 4 | E7: =SUMIFS(Data!$E$5:$E$337,Data!$A$5:$A$337,A7,Data!$C$5:$C$337,"Y") -> 320 | F7: =IFERROR(E7/D7,0) -> 80
A8: Student 05 | B8: =COUNTIFS(Data!$A$5:$A$337,A8) -> 9 | C8: =COUNTIFS(Data!$A$5:$A$337,A8,Data!$C$5:$C$337,"Y") -> 8 | D8: =SUMIFS(Data!$D$5:$D$337,Data!$A$5:$A$337,A8,Data!$C$5:$C$337,"Y")/60 -> 4 | E8: =SUMIFS(Data!$E$5:$E$337,Data!$A$5:$A$337,A8,Data!$C$5:$C$337,"Y") -> 320 | F8: =IFERROR(E8/D8,0) -> 80
A9: Student 06 | B9: =COUNTIFS(Data!$A$5:$A$337,A9) -> 9 | C9: =COUNTIFS(Data!$A$5:$A$337,A9,Data!$C$5:$C$337,"Y") -> 8 | D9: =SUMIFS(Data!$D$5:$D$337,Data!$A$5:$A$337,A9,Data!$C$5:$C$337,"Y")/60 -> 4 | E9: =SUMIFS(Data!$E$5:$E$337,Data!$A$5:$A$337,A9,Data!$C$5:$C$337,"Y") -> 320 | F9: =IFERROR(E9/D9,0) -> 80
A10: Student 07 | B10: =COUNTIFS(Data!$A$5:$A$337,A10) -> 9 | C10: =COUNTIFS(Data!$A$5:$A$337,A10,Data!$C$5:$C$337,"Y") -> 7 | D10: =SUMIFS(Data!$D$5:$D$337,Data!$A$5:$A$337,A10,Data!$C$5:$C$337,"Y")/60 -> 3.5 | E10: =SUMIFS(Data!$E$5:$E$337,Data!$A$5:$A$337,A10,Data!$C$5:$C$337,"Y") -> 280 | F10: =IFERROR(E10/D10,0) -> 80
A11: Student 08 | B11: =COUNTIFS(Data!$A$5:$A$337,A11) -> 9 | C11: =COUNTIFS(Data!$A$5:$A$337,A11,Data!$C$5:$C$337,"Y") -> 8 | D11: =SUMIFS(Data!$D$5:$D$337,Data!$A$5:$A$337,A11,Data!$C$5:$C$337,"Y")/60 -> 4 | E11: =SUMIFS(Data!$E$5:$E$337,Data!$A$5:$A$337,A11,Data!$C$5:$C$337,"Y") -> 320 | F11: =IFERROR(E11/D11,0) -> 80
A12: Student 09 | B12: =COUNTIFS(Data!$A$5:$A$337,A12) -> 9 | C12: =COUNTIFS(Data!$A$5:$A$337,A12,Data!$C$5:$C$337,"Y") -> 8 | D12: =SUMIFS(Data!$D$5:$D$337,Data!$A$5:$A$337,A12,Data!$C$5:$C$337,"Y")/60 -> 4 | E12: =SUMIFS(Data!$E$5:$E$337,Data!$A$5:$A$337,A12,Data!$C$5:$C$337,"Y") -> 320 | F12: =IFERROR(E12/D12,0) -> 80
A13: Student 10 | B13: =COUNTIFS(Data!$A$5:$A$337,A13) -> 9 | C13: =COUNTIFS(Data!$A$5:$A$337,A13,Data!$C$5:$C$337,"Y") -> 9 | D13: =SUMIFS(Data!$D$5:$D$337,Data!$A$5:$A$337,A13,Data!$C$5:$C$337,"Y")/60 -> 4.5 | E13: =SUMIFS(Data!$E$5:$E$337,Data!$A$5:$A$337,A13,Data!$C$5:$C$337,"Y") -> 360 | F13: =IFERROR(E13/D13,0) -> 80
A14: Student 11 | B14: =COUNTIFS(Data!$A$5:$A$337,A14) -> 9 | C14: =COUNTIFS(Data!$A$5:$A$337,A14,Data!$C$5:$C$337,"Y") -> 9 | D14: =SUMIFS(Data!$D$5:$D$337,Data!$A$5:$A$337,A14,Data!$C$5:$C$337,"Y")/60 -> 4.5 | E14: =SUMIFS(Data!$E$5:$E$337,Data!$A$5:$A$337,A14,Data!$C$5:$C$337,"Y") -> 360 | F14: =IFERROR(E14/D14,0) -> 80
A15: Student 12 | B15: =COUNTIFS(Data!$A$5:$A$337,A15) -> 9 | C15: =COUNTIFS(Data!$A$5:$A$337,A15,Data!$C$5:$C$337,"Y") -> 7 | D15: =SUMIFS(Data!$D$5:$D$337,Data!$A$5:$A$337,A15,Data!$C$5:$C$337,"Y")/60 -> 3.5 | E15: =SUMIFS(Data!$E$5:$E$337,Data!$A$5:$A$337,A15,Data!$C$5:$C$337,"Y") -> 280 | F15: =IFERROR(E15/D15,0) -> 80
... A40: Student 37 | B40: =COUNTIFS(Data!$A$5:$A$337,A40) -> 8 | C40: =COUNTIFS(Data!$A$5:$A$337,A40,Data!$C$5:$C$337,"Y") -> 6 | D40: =SUMIFS(Data!$D$5:$D$337,Data!$A$5:$A$337,A40,Data!$C$5:$C$337,"Y")/60 -> 3 | E40: =SUMIFS(Data!$E$5:$E$337,Data!$A$5:$A$337,A40,Data!$C$5:$C$337,"Y") -> 240 | F40: =IFERROR(E40/D40,0) -> 80
A41: TOTAL | B41: =SUM(B4:B40) -> 333 | C41: =SUM(C4:C40) -> 296 | D41: =SUM(D4:D40) -> 148 | E41: =SUM(E4:E40) -> 11840 | F41: =IFERROR(E41/D41,0) -> 80

Sheet Cost to serve
A1: Cost to serve
A2: Period covered: 2026-02-02 to 2026-04-03 (9 weeks, one term). No suburb/location field exists anywhere in the source data, so travel cost and time are modelled as a flat weekly total (Assumptions sheet) allocated across students by their share of lessons delivered, not by per-suburb distance.
A4: Total vehicle running cost (period) | B4: =Assumptions!$B$32*Assumptions!$B$17 -> 882
A5: Total travel time (period, hours) | B5: =Assumptions!$B$25*Assumptions!$B$17 -> 67.5
A7: Student | B7: Lessons delivered | C7: Share of lessons delivered | D7: Allocated travel cost ($) | E7: Allocated travel time (hrs) | F7: Gross revenue ($) | G7: Contribution ($) | H7: Committed hours
A8: ='Revenue by student'!A4 -> Student 01 | B8: ='Revenue by student'!C4 -> 9 | C8: =IFERROR(B8/'Revenue by student'!$C$41,0) -> 0.030405405 | D8: =C8*$B$4 -> 26.817568 | E8: =C8*$B$5 -> 2.0523649 | F8: ='Revenue by student'!E4 -> 360 | G8: =F8-D8 -> 333.18243 | H8: ='Revenue by student'!D4+E8 -> 6.5523649
A9: ='Revenue by student'!A5 -> Student 02 | B9: ='Revenue by student'!C5 -> 9 | C9: =IFERROR(B9/'Revenue by student'!$C$41,0) -> 0.030405405 | D9: =C9*$B$4 -> 26.817568 | E9: =C9*$B$5 -> 2.0523649 | F9: ='Revenue by student'!E5 -> 360 | G9: =F9-D9 -> 333.18243 | H9: ='Revenue by student'!D5+E9 -> 6.5523649
A10: ='Revenue by student'!A6 -> Student 03 | B10: ='Revenue by student'!C6 -> 9 | C10: =IFERROR(B10/'Revenue by student'!$C$41,0) -> 0.030405405 | D10: =C10*$B$4 -> 26.817568 | E10: =C10*$B$5 -> 2.0523649 | F10: ='Revenue by student'!E6 -> 360 | G10: =F10-D10 -> 333.18243 | H10: ='Revenue by student'!D6+E10 -> 6.5523649
A11: ='Revenue by student'!A7 -> Student 04 | B11: ='Revenue by student'!C7 -> 8 | C11: =IFERROR(B11/'Revenue by student'!$C$41,0) -> 0.027027027 | D11: =C11*$B$4 -> 23.837838 | E11: =C11*$B$5 -> 1.8243243 | F11: ='Revenue by student'!E7 -> 320 | G11: =F11-D11 -> 296.16216 | H11: ='Revenue by student'!D7+E11 -> 5.8243243
A12: ='Revenue by student'!A8 -> Student 05 | B12: ='Revenue by student'!C8 -> 8 | C12: =IFERROR(B12/'Revenue by student'!$C$41,0) -> 0.027027027 | D12: =C12*$B$4 -> 23.837838 | E12: =C12*$B$5 -> 1.8243243 | F12: ='Revenue by student'!E8 -> 320 | G12: =F12-D12 -> 296.16216 | H12: ='Revenue by student'!D8+E12 -> 5.8243243
A13: ='Revenue by student'!A9 -> Student 06 | B13: ='Revenue by student'!C9 -> 8 | C13: =IFERROR(B13/'Revenue by student'!$C$41,0) -> 0.027027027 | D13: =C13*$B$4 -> 23.837838 | E13: =C13*$B$5 -> 1.8243243 | F13: ='Revenue by student'!E9 -> 320 | G13: =F13-D13 -> 296.16216 | H13: ='Revenue by student'!D9+E13 -> 5.8243243
A14: ='Revenue by student'!A10 -> Student 07 | B14: ='Revenue by student'!C10 -> 7 | C14: =IFERROR(B14/'Revenue by student'!$C$41,0) -> 0.023648649 | D14: =C14*$B$4 -> 20.858108 | E14: =C14*$B$5 -> 1.5962838 | F14: ='Revenue by student'!E10 -> 280 | G14: =F14-D14 -> 259.14189 | H14: ='Revenue by student'!D10+E14 -> 5.0962838
A15: ='Revenue by student'!A11 -> Student 08 | B15: ='Revenue by student'!C11 -> 8 | C15: =IFERROR(B15/'Revenue by student'!$C$41,0) -> 0.027027027 | D15: =C15*$B$4 -> 23.837838 | E15: =C15*$B$5 -> 1.8243243 | F15: ='Revenue by student'!E11 -> 320 | G15: =F15-D15 -> 296.16216 | H15: ='Revenue by student'!D11+E15 -> 5.8243243
A16: ='Revenue by student'!A12 -> Student 09 | B16: ='Revenue by student'!C12 -> 8 | C16: =IFERROR(B16/'Revenue by student'!$C$41,0) -> 0.027027027 | D16: =C16*$B$4 -> 23.837838 | E16: =C16*$B$5 -> 1.8243243 | F16: ='Revenue by student'!E12 -> 320 | G16: =F16-D16 -> 296.16216 | H16: ='Revenue by student'!D12+E16 -> 5.8243243
A17: ='Revenue by student'!A13 -> Student 10 | B17: ='Revenue by student'!C13 -> 9 | C17: =IFERROR(B17/'Revenue by student'!$C$41,0) -> 0.030405405 | D17: =C17*$B$4 -> 26.817568 | E17: =C17*$B$5 -> 2.0523649 | F17: ='Revenue by student'!E13 -> 360 | G17: =F17-D17 -> 333.18243 | H17: ='Revenue by student'!D13+E17 -> 6.5523649
A18: ='Revenue by student'!A14 -> Student 11 | B18: ='Revenue by student'!C14 -> 9 | C18: =IFERROR(B18/'Revenue by student'!$C$41,0) -> 0.030405405 | D18: =C18*$B$4 -> 26.817568 | E18: =C18*$B$5 -> 2.0523649 | F18: ='Revenue by student'!E14 -> 360 | G18: =F18-D18 -> 333.18243 | H18: ='Revenue by student'!D14+E18 -> 6.5523649
A19: ='Revenue by student'!A15 -> Student 12 | B19: ='Revenue by student'!C15 -> 7 | C19: =IFERROR(B19/'Revenue by student'!$C$41,0) -> 0.023648649 | D19: =C19*$B$4 -> 20.858108 | E19: =C19*$B$5 -> 1.5962838 | F19: ='Revenue by student'!E15 -> 280 | G19: =F19-D19 -> 259.14189 | H19: ='Revenue by student'!D15+E19 -> 5.0962838
... A44: ='Revenue by student'!A40 -> Student 37 | B44: ='Revenue by student'!C40 -> 6 | C44: =IFERROR(B44/'Revenue by student'!$C$41,0) -> 0.02027027 | D44: =C44*$B$4 -> 17.878378 | E44: =C44*$B$5 -> 1.3682432 | F44: ='Revenue by student'!E40 -> 240 | G44: =F44-D44 -> 222.12162 | H44: ='Revenue by student'!D40+E44 -> 4.3682432
A45: TOTAL | B45: =SUM(B8:B44) -> 296 | D45: =SUM(D8:D44) -> 882 | E45: =SUM(E8:E44) -> 67.5 | F45: =SUM(F8:F44) -> 11840 | G45: =SUM(G8:G44) -> 10958 | H45: =SUM(H8:H44) -> 215.5

Sheet Capacity
A1: Capacity
A2: Max lessons/week is a hard ceiling on lesson-delivery time only. Travel time is separate, additive time spent outside it (owner already teaches at the scheduling ceiling), so it is not subtracted here. See Cost to serve for how travel time is treated as unpaid capacity consumed per student.
A4: Max lessons per week (scheduling ceiling) | B4: =Assumptions!$B$20 -> 37
A5: Max teachable hours per week | B5: =Assumptions!$B$21 -> 18.5
A6: Travel time per week (hrs, additive) | B6: =Assumptions!$B$25 -> 7.5 | C6: Not subtracted from teaching ceiling. See note above.
A7: Total weekly time commitment at full capacity | B7: =B5+B6 -> 26 | C7: Teaching ceiling + travel time: the real total workload if fully booked.
A9: Actual hours delivered/week (avg) | B9: ='Revenue by student'!$D$41/Assumptions!$B$17 -> 16.444444 | C9: Averaged over the 9-week extract.
A10: Actual lessons delivered/week (avg) | B10: ='Revenue by student'!$C$41/Assumptions!$B$17 -> 32.888889
A11: Utilisation (actual hrs ÷ max teachable hrs) | B11: =IFERROR(B9/B5,0) -> 0.88888889 | C11: How close to the scheduling ceiling the business ran.
A13: Scheduled lessons/week (avg) | B13: ='Revenue by student'!$B$41/Assumptions!$B$17 -> 37 | C13: Already equal to the max. See note below.
A14: Show-up rate (delivered ÷ scheduled) | B14: =IFERROR(B10/B13,0) -> 0.88888889 | C14: Scheduled already sits at the max lessons/week ceiling, so this equals utilisation above: the constraint here is no-shows/cancellations, not unfilled slots.
A16: Ceiling annual revenue (if every slot delivered) | B16: =B5*Assumptions!$B$18*Assumptions!$B$9 -> 53280 | C16: Max teachable hrs × working weeks/yr × hourly rate.
A17: Actual annualised revenue pace | B17: ='Revenue by student'!$E$41/Assumptions!$B$17*Assumptions!$B$18 -> 47360 | C17: Extrapolated run-rate, NOT an actual full-year figure; the business wound up ~18 Sept 2026.

Sheet P&L and provisioning
A1: P&L and provisioning
A3: Period actuals (9 weeks, from the extract)
A4: Gross revenue | B4: ='Revenue by student'!$E$41 -> 11840
A5: Less: allocated travel cost | B5: =-'Cost to serve'!$D$45 -> -882
A6: Net operating income | B6: =B4+B5 -> 10958
A7: Super provision | B7: =B6*Assumptions!$B$12 -> 1369.75
A8: Taxable income after super | B8: =B6-B7 -> 9588.25
A9: Tax provision | B9: =B8*Assumptions!$B$13 -> 1917.65 | C9: ESTIMATE only. See Assumptions sheet note.
A10: Net income (period) | B10: =B6-B7-B9 -> 7670.6
A13: Annualised run-rate (extrapolated, NOT an actual full-year figure; the business wound up ~18 Sept 2026)
A14: Annualisation factor (working weeks/yr ÷ weeks/term) | B14: =Assumptions!$B$18/Assumptions!$B$17 -> 4
A15: Gross revenue | B15: =B4*$B$14 -> 47360
A16: Less: allocated travel cost | B16: =B5*$B$14 -> -3528
A17: Net operating income | B17: =B6*$B$14 -> 43832
A18: Super provision | B18: =B7*$B$14 -> 5479
A19: Taxable income after super | B19: =B8*$B$14 -> 38353
A20: Tax provision | B20: =B9*$B$14 -> 7670.6
A21: Net income (annualised) | B21: =B10*$B$14 -> 30682.4

Sheet Scenarios
A1: Scenarios
A2: All three columns are live formulas driven by the multipliers on the Assumptions sheet, not separate copied models. Vehicle/travel cost is held constant across scenarios: there's no distance-based driver in the data to scale it with lesson volume.
B4: 1. Base (actual) | C4: 2. More students, current rate | D4: 3. Higher rate, fewer students
A5: Lessons/week (avg) | B5: =Capacity!$B$10 -> 32.888889 | C5: =B5*Assumptions!$B$36 -> 42.755556 | D5: =B5*Assumptions!$B$38 -> 27.955556
A6: Rate per lesson ($) | B6: =Assumptions!$B$7 -> 40 | C6: =Assumptions!$B$7 -> 40 | D6: =Assumptions!$B$7*Assumptions!$B$37 -> 50
A7: Annualised revenue ($) | B7: =B5*Assumptions!$B$18*B6 -> 47360 | C7: =C5*Assumptions!$B$18*C6 -> 61568 | D7: =D5*Assumptions!$B$18*D6 -> 50320
A8: Annualised vehicle/travel cost ($) | B8: =Assumptions!$B$32*Assumptions!$B$18 -> 3528 | C8: =Assumptions!$B$32*Assumptions!$B$18 -> 3528 | D8: =Assumptions!$B$32*Assumptions!$B$18 -> 3528
A9: Net operating income ($) | B9: =B7-B8 -> 43832 | C9: =C7-C8 -> 58040 | D9: =D7-D8 -> 46792
A10: Super provision ($) | B10: =B9*Assumptions!$B$12 -> 5479 | C10: =C9*Assumptions!$B$12 -> 7255 | D10: =D9*Assumptions!$B$12 -> 5849
A11: Taxable income after super ($) | B11: =B9-B10 -> 38353 | C11: =C9-C10 -> 50785 | D11: =D9-D10 -> 40943
A12: Tax provision ($) | B12: =B11*Assumptions!$B$13 -> 7670.6 | C12: =C11*Assumptions!$B$13 -> 10157 | D12: =D11*Assumptions!$B$13 -> 8188.6
A13: Net income (annualised, $) | B13: =B9-B10-B12 -> 30682.4 | C13: =C9-C10-C12 -> 40628 | D13: =D9-D10-D12 -> 32754.4
A15: Selected scenario (Assumptions!scenario_switch) | B15: =CHOOSE(Assumptions!$B$35,B4,C4,D4) -> 1. Base (actual)
A16: Selected scenario net income ($) | B16: =CHOOSE(Assumptions!$B$35,B13,C13,D13) -> 30682.4

Sheet Sensitivity
A1: Sensitivity: net income by rate × utilisation
A2: Explicit formula grid (not a native Excel Data Table). Each cell = (annualised base revenue × row volume multiplier × column rate multiplier − annualised vehicle/travel cost) × (1 − super rate) × (1 − tax rate). Cost is held flat, same simplification as Scenarios.
A4: Base annualised revenue ($) | B4: ='P&L and provisioning'!$B$15 -> 47360
A5: Base annualised vehicle/travel cost ($) | B5: =ABS('P&L and provisioning'!$B$16) -> 3528
A7: Volume ↓ / Rate → | C7: 0.9 | D7: 0.95 | E7: 1 | F7: 1.05 | G7: 1.1
A8: Lesson volume multiplier (row) Rate multiplier (column) → | B8: 0.8 | C8: =(($B$4*$B8*C$7)-$B$5)*(1-Assumptions!$B$12)*(1-Assumptions!$B$13) -> 21399.84 | D8: =(($B$4*$B8*D$7)-$B$5)*(1-Assumptions!$B$12)*(1-Assumptions!$B$13) -> 22725.92 | E8: =(($B$4*$B8*E$7)-$B$5)*(1-Assumptions!$B$12)*(1-Assumptions!$B$13) -> 24052 | F8: =(($B$4*$B8*F$7)-$B$5)*(1-Assumptions!$B$12)*(1-Assumptions!$B$13) -> 25378.08 | G8: =(($B$4*$B8*G$7)-$B$5)*(1-Assumptions!$B$12)*(1-Assumptions!$B$13) -> 26704.16
B9: 0.9 | C9: =(($B$4*$B9*C$7)-$B$5)*(1-Assumptions!$B$12)*(1-Assumptions!$B$13) -> 24383.52 | D9: =(($B$4*$B9*D$7)-$B$5)*(1-Assumptions!$B$12)*(1-Assumptions!$B$13) -> 25875.36 | E9: =(($B$4*$B9*E$7)-$B$5)*(1-Assumptions!$B$12)*(1-Assumptions!$B$13) -> 27367.2 | F9: =(($B$4*$B9*F$7)-$B$5)*(1-Assumptions!$B$12)*(1-Assumptions!$B$13) -> 28859.04 | G9: =(($B$4*$B9*G$7)-$B$5)*(1-Assumptions!$B$12)*(1-Assumptions!$B$13) -> 30350.88
B10: 1 | C10: =(($B$4*$B10*C$7)-$B$5)*(1-Assumptions!$B$12)*(1-Assumptions!$B$13) -> 27367.2 | D10: =(($B$4*$B10*D$7)-$B$5)*(1-Assumptions!$B$12)*(1-Assumptions!$B$13) -> 29024.8 | E10: =(($B$4*$B10*E$7)-$B$5)*(1-Assumptions!$B$12)*(1-Assumptions!$B$13) -> 30682.4 | F10: =(($B$4*$B10*F$7)-$B$5)*(1-Assumptions!$B$12)*(1-Assumptions!$B$13) -> 32340 | G10: =(($B$4*$B10*G$7)-$B$5)*(1-Assumptions!$B$12)*(1-Assumptions!$B$13) -> 33997.6
B11: 1.1 | C11: =(($B$4*$B11*C$7)-$B$5)*(1-Assumptions!$B$12)*(1-Assumptions!$B$13) -> 30350.88 | D11: =(($B$4*$B11*D$7)-$B$5)*(1-Assumptions!$B$12)*(1-Assumptions!$B$13) -> 32174.24 | E11: =(($B$4*$B11*E$7)-$B$5)*(1-Assumptions!$B$12)*(1-Assumptions!$B$13) -> 33997.6 | F11: =(($B$4*$B11*F$7)-$B$5)*(1-Assumptions!$B$12)*(1-Assumptions!$B$13) -> 35820.96 | G11: =(($B$4*$B11*G$7)-$B$5)*(1-Assumptions!$B$12)*(1-Assumptions!$B$13) -> 37644.32
B12: 1.2 | C12: =(($B$4*$B12*C$7)-$B$5)*(1-Assumptions!$B$12)*(1-Assumptions!$B$13) -> 33334.56 | D12: =(($B$4*$B12*D$7)-$B$5)*(1-Assumptions!$B$12)*(1-Assumptions!$B$13) -> 35323.68 | E12: =(($B$4*$B12*E$7)-$B$5)*(1-Assumptions!$B$12)*(1-Assumptions!$B$13) -> 37312.8 | F12: =(($B$4*$B12*F$7)-$B$5)*(1-Assumptions!$B$12)*(1-Assumptions!$B$13) -> 39301.92 | G12: =(($B$4*$B12*G$7)-$B$5)*(1-Assumptions!$B$12)*(1-Assumptions!$B$13) -> 41291.04
